avmesos/__init__.py
avmesos/acs.py
avmesos/client.py
avmesos/core.py
avmesos/exception.py
avmesos/offers.py
avmesos/update.py
avmesos-0.4.2.dist-info/LICENSE
avmesos-0.4.2.dist-info/METADATA
avmesos-0.4.2.dist-info/WHEEL
avmesos-0.4.2.dist-info/top_level.txt
avmesos-0.4.2.dist-info/RECORD
