Metadata-Version: 2.1
Name: avmesos
Version: 0.4.2
Summary: Mesos HTTP lib
Download-URL: https://github.com/AVENTER-UG/python-avmesos
Author: AVENTER UG (haftungsbeschraenkt)
Author-email: support@aventer.biz
Classifier: Development Status :: 5 - Production/Stable
Classifier: Environment :: Console
Classifier: Natural Language :: English
Classifier: Operating System :: POSIX :: Linux
Classifier: Intended Audience :: Science/Research
Classifier: Topic :: Software Development :: Libraries :: Python Modules
Classifier: License :: OSI Approved :: Apache Software License
Classifier: Programming Language :: Python :: 2
Classifier: Programming Language :: Python :: 2.7
Classifier: Programming Language :: Python :: 3
Classifier: Programming Language :: Python :: 3.4
License-File: LICENSE
Requires-Dist: cryptography
Requires-Dist: kazoo
Requires-Dist: pyjwt
Requires-Dist: requests
